README.rst
setup.cfg
setup.py
markov_autocomplete/__init__.py
markov_autocomplete/autocomplete.py
markov_autocomplete.egg-info/PKG-INFO
markov_autocomplete.egg-info/SOURCES.txt
markov_autocomplete.egg-info/dependency_links.txt
markov_autocomplete.egg-info/top_level.txt