Metadata-Version: 1.1
Name: markov-autocomplete
Version: 1.0.1
Summary: Autocomplete model easy to integrate with Flask apps
Home-page: https://github.com/YourMD/markov-autocomplete
Author: Matteo Tomassetti (Data Scientist at Your.MD)
Author-email: matteo.tomassetti@your.md
License: UNKNOWN
Download-URL: https://github.com/YourMD/markov-autocomplete/tarball/autocomplete
Keywords: autocomplete hidden-markov model nlp natural language processing
Platform: UNKNOWN
Classifier: Development Status :: 4 - Beta
Classifier: Intended Audience :: Information Technology
Classifier: Intended Audience :: Science/Research
Classifier: Intended Audience :: Education
Classifier: Topic :: Scientific/Engineering :: Artificial Intelligence
Classifier: License :: OSI Approved :: MIT License
Classifier: Programming Language :: Python :: 3.4
